Metadata-Version: 2.4
Name: aibioagent
Version: 1.0.0
Summary: A multi-agent AI system for biomedical imaging research with RAG, image analysis, and paper review
Home-page: https://github.com/chenli-git/AI_scientist_for_bioimaging
Author: Chen Li
Author-email: Chen Li <chenli970701@gmail.com>
Maintainer-email: Chen Li <chenli970701@gmail.com>
License: MIT License
Project-URL: Homepage, https://github.com/chenli-git/AI_scientist_for_bioimaging
Project-URL: Documentation, https://github.com/chenli-git/AI_scientist_for_bioimaging#readme
Project-URL: Repository, https://github.com/chenli-git/AI_scientist_for_bioimaging
Project-URL: Issues, https://github.com/chenli-git/AI_scientist_for_bioimaging/issues
Keywords: artificial-intelligence,biomedical-imaging,multi-agent-systems,rag,langchain,image-analysis,microscopy
Classifier: Development Status :: 3 - Alpha
Classifier: Intended Audience :: Science/Research
Classifier: Intended Audience :: Healthcare Industry
Classifier: Topic :: Scientific/Engineering :: Artificial Intelligence
Classifier: Topic :: Scientific/Engineering :: Image Processing
Classifier: License :: OSI Approved :: MIT License
Classifier: Programming Language :: Python :: 3
Classifier: Programming Language :: Python :: 3.10
Classifier: Programming Language :: Python :: 3.11
Classifier: Programming Language :: Python :: 3.12
Requires-Python: >=3.10
License-File: LICENSE
Requires-Dist: openai<2.0.0,>=1.43.0
Requires-Dist: langchain<2.0.0,>=0.3.0
Requires-Dist: langchain-core<2.0.0,>=0.3.0
Requires-Dist: langchain-community<1.0.0,>=0.3.0
Requires-Dist: langchain-openai<2.0.0,>=0.1.0
Requires-Dist: langchain-text-splitters<2.0.0,>=0.3.0
Requires-Dist: chromadb<2.0.0,>=0.5.3
Requires-Dist: pypdf<7.0.0,>=4.2.0
Requires-Dist: docling<3.0.0,>=2.50.0
Requires-Dist: tiktoken<1.0.0,>=0.7.0
Requires-Dist: scikit-image<1.0.0,>=0.24.0
Requires-Dist: tifffile>=2025.1.10
Requires-Dist: pillow<12.0.0,>=10.0.0
Requires-Dist: opencv-python<5.0.0,>=4.8.0
Requires-Dist: numpy<3.0.0,>=1.26.0
Requires-Dist: pandas<3.0.0,>=2.2.0
Requires-Dist: beautifulsoup4<5.0.0,>=4.14.0
Requires-Dist: playwright<2.0.0,>=1.50.0
Requires-Dist: requests<3.0.0,>=2.32.0
Requires-Dist: gradio<6.0.0,>=4.44.0
Requires-Dist: python-dotenv<2.0.0,>=1.0.1
Requires-Dist: rich<14.0.0,>=13.7.0
Requires-Dist: tenacity<9.0.0,>=8.3.0
Requires-Dist: pydantic<3.0.0,>=2.0.0
Provides-Extra: dev
Requires-Dist: pytest<9.0.0,>=8.0.0; extra == "dev"
Requires-Dist: pytest-mock<4.0.0,>=3.14.0; extra == "dev"
Requires-Dist: pytest-cov>=4.1.0; extra == "dev"
Requires-Dist: black>=24.0.0; extra == "dev"
Requires-Dist: flake8>=7.0.0; extra == "dev"
Requires-Dist: mypy>=1.8.0; extra == "dev"
Provides-Extra: docs
Requires-Dist: sphinx>=7.0.0; extra == "docs"
Requires-Dist: sphinx-rtd-theme>=2.0.0; extra == "docs"
Dynamic: author
Dynamic: home-page
Dynamic: license-file
Dynamic: requires-python
